gxipy/__init__.py
gxipy/dxwrapper.py
gxipy/gxiapi.py
gxipy/gxidef.py
gxipy/gxwrapper.py
WVTC_PIL-1.0.0.dist-info/LICENSE
WVTC_PIL-1.0.0.dist-info/METADATA
WVTC_PIL-1.0.0.dist-info/WHEEL
WVTC_PIL-1.0.0.dist-info/top_level.txt
WVTC_PIL-1.0.0.dist-info/RECORD
